Workbook

Sheet Start Here
B2: Technical Debt Balance Sheet & Interest Calculator
B3: Companion to "Technical Debt Is a Balance Sheet Liability, Not a Metaphor" (Engineering Economics, Part 7)
B5: What this is
B6: A technical debt balance sheet puts a loan on a ledger: PRINCIPAL (what it costs to clear the debt),
B7: INTEREST (what you pay every year you carry it), and a PAYBACK period (how fast remediation returns the
B8: spend). This tool turns "the codebase is slowing us down" into those three numbers, the ones finance funds.
B10: Blue cells are the only inputs. Everything else is a live formula, so change a blue cell and every result
B11: updates. The defaults reproduce the article's illustrative worked example.
B13: The four tabs
B14: 1. Debt Balance Sheet - the core model. Edit the blue cells; read annual interest, principal, the implied
B15: interest rate, and payback. Start here.
B16: 2. Debt Ceiling - what fraction of your team's total capacity the debt's interest already eats, and how that
... B34: Replace every blue cell with your own.

Sheet Debt Balance Sheet
B2: Debt Balance Sheet
B3: Edit the blue cells. Principal, interest, implied rate, and payback are computed at the bottom.
B5: INPUTS (edit the blue cells)
B6: Loaded engineer hourly cost ($) | C6: 150 | D6: Salary + benefits + payroll tax + equipment + overhead, per hour. Same definition across the whole model series.
B7: Engineers affected by this debt | C7: 6 | D7: How many engineers routinely route around this specific debt.
B8: Hours per engineer per sprint lost to this debt | C8: 8 | D8: Time each affected engineer burns working around the debt, per sprint. Default: 4 hrs/week over a 2-week sprint.
B9: Sprints per year | C9: 26 | D9: Your sprint cadence. 26 two-week sprints = a full year.
B10: Incident-frequency delta per year (extra incidents) | C10: 0 | D10: Extra production incidents per year you attribute to this debt. Default 0 keeps the headline to the velocity cost.
B11: Loaded cost per incident ($) | C11: 0 | D11: Fully-loaded cost of one such incident: responders woken, hours burned, follow-up. 0 if you are not counting incidents yet.
B12: Estimated remediation hours (base) | C12: 1600 | D12: Engineering hours to clear the debt, before the complexity multiplier. Your naive, honest first guess.
B13: Complexity / risk multiplier (x) | C13: 1.25 | D13: Scales remediation for integration, testing, and unknowns. 1.2x for well-isolated, 2x+ for deeply tangled.
B15: These defaults are illustrative, from the article. Replace every blue cell with your own numbers.
B17: HOURS AND CAPACITY
B18: Hours lost per year to this debt (interest, in hours) | C18: =$C$7*$C$8*$C$9 | D18: Engineers x hours per sprint x sprints per year. The debt's interest expressed as time.
B19: Annual interest from lost time ($) | C19: =$C$18*$C$6 | D19: Hours lost per year x loaded hourly rate.
B20: Annual interest from incidents ($) | C20: =$C$10*$C$11 | D20: Extra incidents per year x loaded cost per incident.
B22: THE BALANCE SHEET
B23: Annual interest (total $/yr) | C23: =$C$19+$C$20 | D23: What you pay every year you carry this debt: lost time + incident cost. Paid forever until fixed.
B24: Principal to remediate ($) | C24: =$C$12*$C$6*$C$13 | D24: Remediation hours x loaded rate x complexity multiplier. What it costs to clear the debt once.
B25: Implied annual interest rate (interest / principal) | C25: =IF($C$24=0,"n/a",$C$23/$C$24) | D25: The yearly return on paying the debt down. Above ~50% means remediation pays for itself inside two years.
B26: Payback period (years) | C26: =IF($C$23=0,"n/a",$C$24/$C$23) | D26: Principal / annual interest. How long the saved interest takes to repay the remediation spend.
B27: Payback period (months) | C27: =IF($C$23=0,"n/a",$C$26*12) | D27: The same payback expressed in months.
B29: The one-sentence balance sheet | C29: ="This debt costs about $"&TEXT($C$23,"#,##0")&"/yr in interest, with about $"&TEXT($C$24,"#,##0")&" to remediate, paying back in "&TEXT($C$26*12,"0")&" months (a "&TEXT(IF($C$24=0,0,$C$23/$C$24),"0%")&" first-year return)."

Sheet Debt Ceiling
B2: Debt Ceiling
B3: How much of the team's total capacity the debt's interest eats, and how that climbs toward feature velocity = 0.
B5: TEAM CAPACITY (edit blue cells)
B6: Total engineers on the team | C6: 6 | D6: The whole team whose capacity you are measuring against (may be larger than the engineers this one debt slows).
B7: Working hours per engineer per sprint | C7: 60 | D7: Usable engineering hours per engineer per sprint. Default: ~30 hrs/week over a 2-week sprint.
B9: Total team capacity (hours/year) | C9: =$C$6*$C$7*'Debt Balance Sheet'!$C$9 | D9: Total engineers x working hours per sprint x sprints per year.
B10: Debt interest at current assumption (hours/year) | C10: ='Debt Balance Sheet'!$C$18 | D10: Pulled from the Debt Balance Sheet tab (engineers x hours/sprint x sprints/yr).
B11: Fraction of total capacity consumed by interest (now) | C11: =IF($C$9=0,"n/a",C10/$C$9) | D11: Every hour here is an hour of feature capacity the debt has already taken off the table.
B13: PROJECTION: as the velocity loss grows, the interest eats more of total capacity
B14: Each row raises hours-lost-per-engineer-per-sprint. The ceiling is where interest approaches total capacity (velocity -> 0).
B15: Hours lost / eng / sprint | C15: Interest (hours/year) | D15: Share of total capacity | E15: Status
B16: 2 | C16: ='Debt Balance Sheet'!$C$7*B16*'Debt Balance Sheet'!$C$9 | D16: =IF($C$9=0,"n/a",C16/$C$9) | E16: =IF(C16/$C$9>=1,"CEILING: velocity ~0",IF(C16/$C$9>=0.5,"Danger: majority of capacity",IF(C16/$C$9>=0.25,"Warning: climbing","OK")))
B17: 4 | C17: ='Debt Balance Sheet'!$C$7*B17*'Debt Balance Sheet'!$C$9 | D17: =IF($C$9=0,"n/a",C17/$C$9) | E17: =IF(C17/$C$9>=1,"CEILING: velocity ~0",IF(C17/$C$9>=0.5,"Danger: majority of capacity",IF(C17/$C$9>=0.25,"Warning: climbing","OK")))
B18: 6 | C18: ='Debt Balance Sheet'!$C$7*B18*'Debt Balance Sheet'!$C$9 | D18: =IF($C$9=0,"n/a",C18/$C$9) | E18: =IF(C18/$C$9>=1,"CEILING: velocity ~0",IF(C18/$C$9>=0.5,"Danger: majority of capacity",IF(C18/$C$9>=0.25,"Warning: climbing","OK")))
B19: 8 | C19: ='Debt Balance Sheet'!$C$7*B19*'Debt Balance Sheet'!$C$9 | D19: =IF($C$9=0,"n/a",C19/$C$9) | E19: =IF(C19/$C$9>=1,"CEILING: velocity ~0",IF(C19/$C$9>=0.5,"Danger: majority of capacity",IF(C19/$C$9>=0.25,"Warning: climbing","OK")))
B20: 10 | C20: ='Debt Balance Sheet'!$C$7*B20*'Debt Balance Sheet'!$C$9 | D20: =IF($C$9=0,"n/a",C20/$C$9) | E20: =IF(C20/$C$9>=1,"CEILING: velocity ~0",IF(C20/$C$9>=0.5,"Danger: majority of capacity",IF(C20/$C$9>=0.25,"Warning: climbing","OK")))
B21: 12 | C21: ='Debt Balance Sheet'!$C$7*B21*'Debt Balance Sheet'!$C$9 | D21: =IF($C$9=0,"n/a",C21/$C$9) | E21: =IF(C21/$C$9>=1,"CEILING: velocity ~0",IF(C21/$C$9>=0.5,"Danger: majority of capacity",IF(C21/$C$9>=0.25,"Warning: climbing","OK")))
B22: 15 | C22: ='Debt Balance Sheet'!$C$7*B22*'Debt Balance Sheet'!$C$9 | D22: =IF($C$9=0,"n/a",C22/$C$9) | E22: =IF(C22/$C$9>=1,"CEILING: velocity ~0",IF(C22/$C$9>=0.5,"Danger: majority of capacity",IF(C22/$C$9>=0.25,"Warning: climbing","OK")))
B23: 20 | C23: ='Debt Balance Sheet'!$C$7*B23*'Debt Balance Sheet'!$C$9 | D23: =IF($C$9=0,"n/a",C23/$C$9) | E23: =IF(C23/$C$9>=1,"CEILING: velocity ~0",IF(C23/$C$9>=0.5,"Danger: majority of capacity",IF(C23/$C$9>=0.25,"Warning: climbing","OK")))
B24: 25 | C24: ='Debt Balance Sheet'!$C$7*B24*'Debt Balance Sheet'!$C$9 | D24: =IF($C$9=0,"n/a",C24/$C$9) | E24: =IF(C24/$C$9>=1,"CEILING: velocity ~0",IF(C24/$C$9>=0.5,"Danger: majority of capacity",IF(C24/$C$9>=0.25,"Warning: climbing","OK")))
B25: 30 | C25: ='Debt Balance Sheet'!$C$7*B25*'Debt Balance Sheet'!$C$9 | D25: =IF($C$9=0,"n/a",C25/$C$9) | E25: =IF(C25/$C$9>=1,"CEILING: velocity ~0",IF(C25/$C$9>=0.5,"Danger: majority of capacity",IF(C25/$C$9>=0.25,"Warning: climbing","OK")))
B27: The ceiling is not hypothetical: when interest approaches total capacity, everyone is busy and nothing ships.

Sheet Sensitivity
B2: Sensitivity: hours lost per sprint
B3: The hours-lost-per-sprint number is the one you are least sure of. This sweeps it and shows how the balance sheet moves.
B5: Hours lost / eng / sprint | C5: Annual interest ($) | D5: Implied interest rate | E5: Payback (months)
B6: 2 | C6: ='Debt Balance Sheet'!$C$7*B6*'Debt Balance Sheet'!$C$9*'Debt Balance Sheet'!$C$6+'Debt Balance Sheet'!$C$20 | D6: =IF('Debt Balance Sheet'!$C$24=0,"n/a",C6/'Debt Balance Sheet'!$C$24) | E6: =IF(C6=0,"n/a",'Debt Balance Sheet'!$C$24/C6*12)
B7: 4 | C7: ='Debt Balance Sheet'!$C$7*B7*'Debt Balance Sheet'!$C$9*'Debt Balance Sheet'!$C$6+'Debt Balance Sheet'!$C$20 | D7: =IF('Debt Balance Sheet'!$C$24=0,"n/a",C7/'Debt Balance Sheet'!$C$24) | E7: =IF(C7=0,"n/a",'Debt Balance Sheet'!$C$24/C7*12)
B8: 6 | C8: ='Debt Balance Sheet'!$C$7*B8*'Debt Balance Sheet'!$C$9*'Debt Balance Sheet'!$C$6+'Debt Balance Sheet'!$C$20 | D8: =IF('Debt Balance Sheet'!$C$24=0,"n/a",C8/'Debt Balance Sheet'!$C$24) | E8: =IF(C8=0,"n/a",'Debt Balance Sheet'!$C$24/C8*12)
B9: 8 | C9: ='Debt Balance Sheet'!$C$7*B9*'Debt Balance Sheet'!$C$9*'Debt Balance Sheet'!$C$6+'Debt Balance Sheet'!$C$20 | D9: =IF('Debt Balance Sheet'!$C$24=0,"n/a",C9/'Debt Balance Sheet'!$C$24) | E9: =IF(C9=0,"n/a",'Debt Balance Sheet'!$C$24/C9*12)
B10: 10 | C10: ='Debt Balance Sheet'!$C$7*B10*'Debt Balance Sheet'!$C$9*'Debt Balance Sheet'!$C$6+'Debt Balance Sheet'!$C$20 | D10: =IF('Debt Balance Sheet'!$C$24=0,"n/a",C10/'Debt Balance Sheet'!$C$24) | E10: =IF(C10=0,"n/a",'Debt Balance Sheet'!$C$24/C10*12)
B11: 12 | C11: ='Debt Balance Sheet'!$C$7*B11*'Debt Balance Sheet'!$C$9*'Debt Balance Sheet'!$C$6+'Debt Balance Sheet'!$C$20 | D11: =IF('Debt Balance Sheet'!$C$24=0,"n/a",C11/'Debt Balance Sheet'!$C$24) | E11: =IF(C11=0,"n/a",'Debt Balance Sheet'!$C$24/C11*12)
B12: 15 | C12: ='Debt Balance Sheet'!$C$7*B12*'Debt Balance Sheet'!$C$9*'Debt Balance Sheet'!$C$6+'Debt Balance Sheet'!$C$20 | D12: =IF('Debt Balance Sheet'!$C$24=0,"n/a",C12/'Debt Balance Sheet'!$C$24) | E12: =IF(C12=0,"n/a",'Debt Balance Sheet'!$C$24/C12*12)
B13: 20 | C13: ='Debt Balance Sheet'!$C$7*B13*'Debt Balance Sheet'!$C$9*'Debt Balance Sheet'!$C$6+'Debt Balance Sheet'!$C$20 | D13: =IF('Debt Balance Sheet'!$C$24=0,"n/a",C13/'Debt Balance Sheet'!$C$24) | E13: =IF(C13=0,"n/a",'Debt Balance Sheet'!$C$24/C13*12)
B15: If the implied rate and payback barely move across the range, trust the call. If they swing, go measure the hours before you decide.
B16: The row at 8 hrs/sprint is the article's default: ~$187K/yr interest on one module.
