Workbook

Sheet Start Here
B2: Migration Crossover Calculator
B3: Companion to "The Economics of Migration: Sunk Cost vs. Rip-and-Replace" (Engineering Economics, Part 6)
B5: What this answers
B6: Keeping an aging system is cheaper than migrating EVERY SINGLE YEAR, right up to and past the point
B7: where it isn't. This tool finds that point: the crossover year when the cumulative cost of keeping the
B8: old system passes the cumulative cost of replacing it. After that year, every year of "one more year"
B9: is dead loss, even though each individual year still looks cheaper.
B11: Sunk cost is deliberately absent. Money already spent is gone under every option, so it does not appear
B12: anywhere in this model. Only forward-looking costs move the answer.
B14: The three tabs
B15: 1. Crossover Calculator - the core model. Edit the blue cells; read the crossover year. Start here.
B16: 2. Hidden Costs of Not Migrating - adds attrition, security, opportunity, and velocity costs to the
... B33: a decade-plus of locally-reasonable deferrals, each one pushing the replacement cost higher.

Sheet Crossover Calculator
B2: Crossover Calculator
B3: Edit the blue cells. The crossover year is computed at the bottom.
B5: INPUTS (edit the blue cells)
B6: Time horizon (years) | C6: 7 | D6: How many years to project. 7-10 is usually enough to see the crossover.
B7: Current annual maintenance of old system ($) | C7: 600000 | D7: What the old system costs to keep running THIS year.
B8: Annual maintenance growth rate (%) | C8: 0.2 | D8: How fast that cost rises as the system ages. 10-20% is common for genuinely aging systems.
B9: One-time migration cost ($) | C9: 2000000 | D9: Full cost to replace: build + dual-run + data + integration + retraining + testing.
B10: Migration realism multiplier (x) | C10: 1 | D10: Set to 2.0 to apply the 2x rule of thumb to an engineering-only estimate. 1.0 if your number is already honest.
B11: New system annual run cost ($) | C11: 150000 | D11: What the replacement costs to operate each year once live.
B13: Effective migration cost (base x multiplier) | C13: =$C$9*$C$10
B15: Year | C15: Annual maint (keep) | D15: Cumulative: KEEP | E15: Cumulative: REPLACE | F15: Cheaper so far | G15: Gap (keep - replace)
B16: 1 | C16: =IF(1<=$C$6,$C$7*(1+$C$8)^(1-1),"") | D16: =IF(1<=$C$6,C16,"") | E16: =IF(1<=$C$6,$C$13+$C$11*1,"") | F16: =IF(1<=$C$6,IF(D16<=E16,"Keep","REPLACE"),"") | G16: =IF(1<=$C$6,D16-E16,"")
B17: 2 | C17: =IF(2<=$C$6,$C$7*(1+$C$8)^(2-1),"") | D17: =IF(2<=$C$6,D16+C17,"") | E17: =IF(2<=$C$6,$C$13+$C$11*2,"") | F17: =IF(2<=$C$6,IF(D17<=E17,"Keep","REPLACE"),"") | G17: =IF(2<=$C$6,D17-E17,"")
B18: 3 | C18: =IF(3<=$C$6,$C$7*(1+$C$8)^(3-1),"") | D18: =IF(3<=$C$6,D17+C18,"") | E18: =IF(3<=$C$6,$C$13+$C$11*3,"") | F18: =IF(3<=$C$6,IF(D18<=E18,"Keep","REPLACE"),"") | G18: =IF(3<=$C$6,D18-E18,"")
B19: 4 | C19: =IF(4<=$C$6,$C$7*(1+$C$8)^(4-1),"") | D19: =IF(4<=$C$6,D18+C19,"") | E19: =IF(4<=$C$6,$C$13+$C$11*4,"") | F19: =IF(4<=$C$6,IF(D19<=E19,"Keep","REPLACE"),"") | G19: =IF(4<=$C$6,D19-E19,"")
B20: 5 | C20: =IF(5<=$C$6,$C$7*(1+$C$8)^(5-1),"") | D20: =IF(5<=$C$6,D19+C20,"") | E20: =IF(5<=$C$6,$C$13+$C$11*5,"") | F20: =IF(5<=$C$6,IF(D20<=E20,"Keep","REPLACE"),"") | G20: =IF(5<=$C$6,D20-E20,"")
B21: 6 | C21: =IF(6<=$C$6,$C$7*(1+$C$8)^(6-1),"") | D21: =IF(6<=$C$6,D20+C21,"") | E21: =IF(6<=$C$6,$C$13+$C$11*6,"") | F21: =IF(6<=$C$6,IF(D21<=E21,"Keep","REPLACE"),"") | G21: =IF(6<=$C$6,D21-E21,"")
B22: 7 | C22: =IF(7<=$C$6,$C$7*(1+$C$8)^(7-1),"") | D22: =IF(7<=$C$6,D21+C22,"") | E22: =IF(7<=$C$6,$C$13+$C$11*7,"") | F22: =IF(7<=$C$6,IF(D22<=E22,"Keep","REPLACE"),"") | G22: =IF(7<=$C$6,D22-E22,"")
B23: 8 | C23: =IF(8<=$C$6,$C$7*(1+$C$8)^(8-1),"") | D23: =IF(8<=$C$6,D22+C23,"") | E23: =IF(8<=$C$6,$C$13+$C$11*8,"") | F23: =IF(8<=$C$6,IF(D23<=E23,"Keep","REPLACE"),"") | G23: =IF(8<=$C$6,D23-E23,"")
B24: 9 | C24: =IF(9<=$C$6,$C$7*(1+$C$8)^(9-1),"") | D24: =IF(9<=$C$6,D23+C24,"") | E24: =IF(9<=$C$6,$C$13+$C$11*9,"") | F24: =IF(9<=$C$6,IF(D24<=E24,"Keep","REPLACE"),"") | G24: =IF(9<=$C$6,D24-E24,"")
B25: 10 | C25: =IF(10<=$C$6,$C$7*(1+$C$8)^(10-1),"") | D25: =IF(10<=$C$6,D24+C25,"") | E25: =IF(10<=$C$6,$C$13+$C$11*10,"") | F25: =IF(10<=$C$6,IF(D25<=E25,"Keep","REPLACE"),"") | G25: =IF(10<=$C$6,D25-E25,"")
B26: 11 | C26: =IF(11<=$C$6,$C$7*(1+$C$8)^(11-1),"") | D26: =IF(11<=$C$6,D25+C26,"") | E26: =IF(11<=$C$6,$C$13+$C$11*11,"") | F26: =IF(11<=$C$6,IF(D26<=E26,"Keep","REPLACE"),"") | G26: =IF(11<=$C$6,D26-E26,"")
B27: 12 | C27: =IF(12<=$C$6,$C$7*(1+$C$8)^(12-1),"") | D27: =IF(12<=$C$6,D26+C27,"") | E27: =IF(12<=$C$6,$C$13+$C$11*12,"") | F27: =IF(12<=$C$6,IF(D27<=E27,"Keep","REPLACE"),"") | G27: =IF(12<=$C$6,D27-E27,"")
B28: 13 | C28: =IF(13<=$C$6,$C$7*(1+$C$8)^(13-1),"") | D28: =IF(13<=$C$6,D27+C28,"") | E28: =IF(13<=$C$6,$C$13+$C$11*13,"") | F28: =IF(13<=$C$6,IF(D28<=E28,"Keep","REPLACE"),"") | G28: =IF(13<=$C$6,D28-E28,"")
B29: 14 | C29: =IF(14<=$C$6,$C$7*(1+$C$8)^(14-1),"") | D29: =IF(14<=$C$6,D28+C29,"") | E29: =IF(14<=$C$6,$C$13+$C$11*14,"") | F29: =IF(14<=$C$6,IF(D29<=E29,"Keep","REPLACE"),"") | G29: =IF(14<=$C$6,D29-E29,"")
B30: 15 | C30: =IF(15<=$C$6,$C$7*(1+$C$8)^(15-1),"") | D30: =IF(15<=$C$6,D29+C30,"") | E30: =IF(15<=$C$6,$C$13+$C$11*15,"") | F30: =IF(15<=$C$6,IF(D30<=E30,"Keep","REPLACE"),"") | G30: =IF(15<=$C$6,D30-E30,"")
B32: RESULT
B33: Crossover year (keep passes replace) | C33: =IFERROR(MATCH("REPLACE",F16:F30,0),"beyond horizon")
B34: Interpretation | C34: =IF(ISNUMBER(C33),"Migrate by year "&C33&". Before it, deferring is defensible. After it, every year of delay is dead loss.","Keeping is still cheaper across your whole horizon. Re-check as maintenance rises or extend the horizon.")

Sheet Hidden Costs of Not Migrating
B2: Hidden Costs of Not Migrating
B3: The "keep" line is never just the maintenance invoice. Add the hidden tax and watch the crossover move earlier.
B5: EXTRA ANNUAL COST OF KEEPING THE OLD SYSTEM (edit blue cells)
B6: Talent attrition / premium to staff legacy skills ($/yr) | C6: 120000 | D6: Higher comp for scarce skills + cost of churn and backfill gaps.
B7: Security exposure (risk-weighted $/yr) | C7: 80000 | D7: Expected annual cost of an unpatched/unsupported vulnerability surface.
B8: Opportunity cost of maintenance capacity ($/yr) | C8: 250000 | D8: Value of what your best people would build if they were not maintaining this.
B9: Competitive / feature-velocity drag ($/yr) | C9: 100000 | D9: Revenue or market cost of shipping slower than competitors on the old platform.
B11: Total hidden tax per year ($) | C11: =SUM(C6:C9)
B13: This tab reuses the Crossover Calculator inputs and adds the hidden tax to the KEEP line each year.
B15: Year | C15: KEEP (maint only) | D15: KEEP (maint + hidden tax) | E15: Cumulative: REPLACE | F15: Cheaper so far (with hidden tax)
B16: 1 | C16: =IF(1<='Crossover Calculator'!$C$6,'Crossover Calculator'!$C$7*(1+'Crossover Calculator'!$C$8)^(1-1),"") | D16: =IF(1<='Crossover Calculator'!$C$6,C16+$C$11*1,"") | E16: =IF(1<='Crossover Calculator'!$C$6,'Crossover Calculator'!$C$13+'Crossover Calculator'!$C$11*1,"") | F16: =IF(1<='Crossover Calculator'!$C$6,IF(D16<=E16,"Keep","REPLACE"),"")
B17: 2 | C17: =IF(2<='Crossover Calculator'!$C$6,C16+'Crossover Calculator'!$C$7*(1+'Crossover Calculator'!$C$8)^(2-1),"") | D17: =IF(2<='Crossover Calculator'!$C$6,C17+$C$11*2,"") | E17: =IF(2<='Crossover Calculator'!$C$6,'Crossover Calculator'!$C$13+'Crossover Calculator'!$C$11*2,"") | F17: =IF(2<='Crossover Calculator'!$C$6,IF(D17<=E17,"Keep","REPLACE"),"")
B18: 3 | C18: =IF(3<='Crossover Calculator'!$C$6,C17+'Crossover Calculator'!$C$7*(1+'Crossover Calculator'!$C$8)^(3-1),"") | D18: =IF(3<='Crossover Calculator'!$C$6,C18+$C$11*3,"") | E18: =IF(3<='Crossover Calculator'!$C$6,'Crossover Calculator'!$C$13+'Crossover Calculator'!$C$11*3,"") | F18: =IF(3<='Crossover Calculator'!$C$6,IF(D18<=E18,"Keep","REPLACE"),"")
B19: 4 | C19: =IF(4<='Crossover Calculator'!$C$6,C18+'Crossover Calculator'!$C$7*(1+'Crossover Calculator'!$C$8)^(4-1),"") | D19: =IF(4<='Crossover Calculator'!$C$6,C19+$C$11*4,"") | E19: =IF(4<='Crossover Calculator'!$C$6,'Crossover Calculator'!$C$13+'Crossover Calculator'!$C$11*4,"") | F19: =IF(4<='Crossover Calculator'!$C$6,IF(D19<=E19,"Keep","REPLACE"),"")
B20: 5 | C20: =IF(5<='Crossover Calculator'!$C$6,C19+'Crossover Calculator'!$C$7*(1+'Crossover Calculator'!$C$8)^(5-1),"") | D20: =IF(5<='Crossover Calculator'!$C$6,C20+$C$11*5,"") | E20: =IF(5<='Crossover Calculator'!$C$6,'Crossover Calculator'!$C$13+'Crossover Calculator'!$C$11*5,"") | F20: =IF(5<='Crossover Calculator'!$C$6,IF(D20<=E20,"Keep","REPLACE"),"")
B21: 6 | C21: =IF(6<='Crossover Calculator'!$C$6,C20+'Crossover Calculator'!$C$7*(1+'Crossover Calculator'!$C$8)^(6-1),"") | D21: =IF(6<='Crossover Calculator'!$C$6,C21+$C$11*6,"") | E21: =IF(6<='Crossover Calculator'!$C$6,'Crossover Calculator'!$C$13+'Crossover Calculator'!$C$11*6,"") | F21: =IF(6<='Crossover Calculator'!$C$6,IF(D21<=E21,"Keep","REPLACE"),"")
B22: 7 | C22: =IF(7<='Crossover Calculator'!$C$6,C21+'Crossover Calculator'!$C$7*(1+'Crossover Calculator'!$C$8)^(7-1),"") | D22: =IF(7<='Crossover Calculator'!$C$6,C22+$C$11*7,"") | E22: =IF(7<='Crossover Calculator'!$C$6,'Crossover Calculator'!$C$13+'Crossover Calculator'!$C$11*7,"") | F22: =IF(7<='Crossover Calculator'!$C$6,IF(D22<=E22,"Keep","REPLACE"),"")
B23: 8 | C23: =IF(8<='Crossover Calculator'!$C$6,C22+'Crossover Calculator'!$C$7*(1+'Crossover Calculator'!$C$8)^(8-1),"") | D23: =IF(8<='Crossover Calculator'!$C$6,C23+$C$11*8,"") | E23: =IF(8<='Crossover Calculator'!$C$6,'Crossover Calculator'!$C$13+'Crossover Calculator'!$C$11*8,"") | F23: =IF(8<='Crossover Calculator'!$C$6,IF(D23<=E23,"Keep","REPLACE"),"")
B24: 9 | C24: =IF(9<='Crossover Calculator'!$C$6,C23+'Crossover Calculator'!$C$7*(1+'Crossover Calculator'!$C$8)^(9-1),"") | D24: =IF(9<='Crossover Calculator'!$C$6,C24+$C$11*9,"") | E24: =IF(9<='Crossover Calculator'!$C$6,'Crossover Calculator'!$C$13+'Crossover Calculator'!$C$11*9,"") | F24: =IF(9<='Crossover Calculator'!$C$6,IF(D24<=E24,"Keep","REPLACE"),"")
B25: 10 | C25: =IF(10<='Crossover Calculator'!$C$6,C24+'Crossover Calculator'!$C$7*(1+'Crossover Calculator'!$C$8)^(10-1),"") | D25: =IF(10<='Crossover Calculator'!$C$6,C25+$C$11*10,"") | E25: =IF(10<='Crossover Calculator'!$C$6,'Crossover Calculator'!$C$13+'Crossover Calculator'!$C$11*10,"") | F25: =IF(10<='Crossover Calculator'!$C$6,IF(D25<=E25,"Keep","REPLACE"),"")
B26: 11 | C26: =IF(11<='Crossover Calculator'!$C$6,C25+'Crossover Calculator'!$C$7*(1+'Crossover Calculator'!$C$8)^(11-1),"") | D26: =IF(11<='Crossover Calculator'!$C$6,C26+$C$11*11,"") | E26: =IF(11<='Crossover Calculator'!$C$6,'Crossover Calculator'!$C$13+'Crossover Calculator'!$C$11*11,"") | F26: =IF(11<='Crossover Calculator'!$C$6,IF(D26<=E26,"Keep","REPLACE"),"")
B27: 12 | C27: =IF(12<='Crossover Calculator'!$C$6,C26+'Crossover Calculator'!$C$7*(1+'Crossover Calculator'!$C$8)^(12-1),"") | D27: =IF(12<='Crossover Calculator'!$C$6,C27+$C$11*12,"") | E27: =IF(12<='Crossover Calculator'!$C$6,'Crossover Calculator'!$C$13+'Crossover Calculator'!$C$11*12,"") | F27: =IF(12<='Crossover Calculator'!$C$6,IF(D27<=E27,"Keep","REPLACE"),"")
B28: 13 | C28: =IF(13<='Crossover Calculator'!$C$6,C27+'Crossover Calculator'!$C$7*(1+'Crossover Calculator'!$C$8)^(13-1),"") | D28: =IF(13<='Crossover Calculator'!$C$6,C28+$C$11*13,"") | E28: =IF(13<='Crossover Calculator'!$C$6,'Crossover Calculator'!$C$13+'Crossover Calculator'!$C$11*13,"") | F28: =IF(13<='Crossover Calculator'!$C$6,IF(D28<=E28,"Keep","REPLACE"),"")
B29: 14 | C29: =IF(14<='Crossover Calculator'!$C$6,C28+'Crossover Calculator'!$C$7*(1+'Crossover Calculator'!$C$8)^(14-1),"") | D29: =IF(14<='Crossover Calculator'!$C$6,C29+$C$11*14,"") | E29: =IF(14<='Crossover Calculator'!$C$6,'Crossover Calculator'!$C$13+'Crossover Calculator'!$C$11*14,"") | F29: =IF(14<='Crossover Calculator'!$C$6,IF(D29<=E29,"Keep","REPLACE"),"")
B30: 15 | C30: =IF(15<='Crossover Calculator'!$C$6,C29+'Crossover Calculator'!$C$7*(1+'Crossover Calculator'!$C$8)^(15-1),"") | D30: =IF(15<='Crossover Calculator'!$C$6,C30+$C$11*15,"") | E30: =IF(15<='Crossover Calculator'!$C$6,'Crossover Calculator'!$C$13+'Crossover Calculator'!$C$11*15,"") | F30: =IF(15<='Crossover Calculator'!$C$6,IF(D30<=E30,"Keep","REPLACE"),"")
B32: Crossover year WITH hidden tax | C32: =IFERROR(MATCH("REPLACE",F16:F30,0),"beyond horizon")
B33: Crossover year WITHOUT hidden tax (from Calculator) | C33: ='Crossover Calculator'!C33
B34: The hidden tax almost always pulls the crossover earlier. That gap is the cost of pretending keeping is free.

Sheet Sensitivity
B2: Sensitivity: maintenance growth rate
B3: The growth rate is the number you are least sure of. This sweeps it and shows how the crossover year moves.
B5: Growth rate | C5: Crossover year | D5: Read | H5: y1 | I5: y2 | J5: y3 | K5: y4 | L5: y5 | M5: y6 | N5: y7 | O5: y8 | P5: y9 | Q5: y10 | R5: y11 | S5: y12 | T5: y13 | U5: y14 | V5: y15
B6: 0.05 | C6: =IF(COUNTIF(H6:V6,"<=0")=15,"beyond 15y",COUNTIF(H6:V6,"<=0")+1) | D6: =IF(ISNUMBER(C6),"Migrate by year "&C6,"holds past 15y") | H6: ='Crossover Calculator'!$C$7*((1+B6)^1-1)/B6-('Crossover Calculator'!$C$13+'Crossover Calculator'!$C$11*1) | I6: ='Crossover Calculator'!$C$7*((1+B6)^2-1)/B6-('Crossover Calculator'!$C$13+'Crossover Calculator'!$C$11*2) | J6: ='Crossover Calculator'!$C$7*((1+B6)^3-1)/B6-('Crossover Calculator'!$C$13+'Crossover Calculator'!$C$11*3) | K6: ='Crossover Calculator'!$C$7*((1+B6)^4-1)/B6-('Crossover Calculator'!$C$13+'Crossover Calculator'!$C$11*4) | L6: ='Crossover Calculator'!$C$7*((1+B6)^5-1)/B6-('Crossover Calculator'!$C$13+'Crossover Calculator'!$C$11*5) | M6: ='Crossover Calculator'!$C$7*((1+B6)^6-1)/B6-('Crossover Calculator'!$C$13+'Crossover Calculator'!$C$11*6) | N6: ='Crossover Calculator'!$C$7*((1+B6)^7-1)/B6-('Crossover Calculator'!$C$13+'Crossover Calculator'!$C$11*7) | O6: ='Crossover Calculator'!$C$7*((1+B6)^8-1)/B6-('Crossover Calculator'!$C$13+'Crossover Calculator'!$C$11*8) | P6: ='Crossover Calculator'!$C$7*((1+B6)^9-1)/B6-('Crossover Calculator'!$C$13+'Crossover Calculator'!$C$11*9) | Q6: ='Crossover Calculator'!$C$7*((1+B6)^10-1)/B6-('Crossover Calculator'!$C$13+'Crossover Calculator'!$C$11*10) | R6: ='Crossover Calculator'!$C$7*((1+B6)^11-1)/B6-('Crossover Calculator'!$C$13+'Crossover Calculator'!$C$11*11) | S6: ='Crossover Calculator'!$C$7*((1+B6)^12-1)/B6-('Crossover Calculator'!$C$13+'Crossover Calculator'!$C$11*12) | T6: ='Crossover Calculator'!$C$7*((1+B6)^13-1)/B6-('Crossover Calculator'!$C$13+'Crossover Calculator'!$C$11*13) | U6: ='Crossover Calculator'!$C$7*((1+B6)^14-1)/B6-('Crossover Calculator'!$C$13+'Crossover Calculator'!$C$11*14) | V6: ='Crossover Calculator'!$C$7*((1+B6)^15-1)/B6-('Crossover Calculator'!$C$13+'Crossover Calculator'!$C$11*15)
B7: 0.1 | C7: =IF(COUNTIF(H7:V7,"<=0")=15,"beyond 15y",COUNTIF(H7:V7,"<=0")+1) | D7: =IF(ISNUMBER(C7),"Migrate by year "&C7,"holds past 15y") | H7: ='Crossover Calculator'!$C$7*((1+B7)^1-1)/B7-('Crossover Calculator'!$C$13+'Crossover Calculator'!$C$11*1) | I7: ='Crossover Calculator'!$C$7*((1+B7)^2-1)/B7-('Crossover Calculator'!$C$13+'Crossover Calculator'!$C$11*2) | J7: ='Crossover Calculator'!$C$7*((1+B7)^3-1)/B7-('Crossover Calculator'!$C$13+'Crossover Calculator'!$C$11*3) | K7: ='Crossover Calculator'!$C$7*((1+B7)^4-1)/B7-('Crossover Calculator'!$C$13+'Crossover Calculator'!$C$11*4) | L7: ='Crossover Calculator'!$C$7*((1+B7)^5-1)/B7-('Crossover Calculator'!$C$13+'Crossover Calculator'!$C$11*5) | M7: ='Crossover Calculator'!$C$7*((1+B7)^6-1)/B7-('Crossover Calculator'!$C$13+'Crossover Calculator'!$C$11*6) | N7: ='Crossover Calculator'!$C$7*((1+B7)^7-1)/B7-('Crossover Calculator'!$C$13+'Crossover Calculator'!$C$11*7) | O7: ='Crossover Calculator'!$C$7*((1+B7)^8-1)/B7-('Crossover Calculator'!$C$13+'Crossover Calculator'!$C$11*8) | P7: ='Crossover Calculator'!$C$7*((1+B7)^9-1)/B7-('Crossover Calculator'!$C$13+'Crossover Calculator'!$C$11*9) | Q7: ='Crossover Calculator'!$C$7*((1+B7)^10-1)/B7-('Crossover Calculator'!$C$13+'Crossover Calculator'!$C$11*10) | R7: ='Crossover Calculator'!$C$7*((1+B7)^11-1)/B7-('Crossover Calculator'!$C$13+'Crossover Calculator'!$C$11*11) | S7: ='Crossover Calculator'!$C$7*((1+B7)^12-1)/B7-('Crossover Calculator'!$C$13+'Crossover Calculator'!$C$11*12) | T7: ='Crossover Calculator'!$C$7*((1+B7)^13-1)/B7-('Crossover Calculator'!$C$13+'Crossover Calculator'!$C$11*13) | U7: ='Crossover Calculator'!$C$7*((1+B7)^14-1)/B7-('Crossover Calculator'!$C$13+'Crossover Calculator'!$C$11*14) | V7: ='Crossover Calculator'!$C$7*((1+B7)^15-1)/B7-('Crossover Calculator'!$C$13+'Crossover Calculator'!$C$11*15)
B8: 0.15 | C8: =IF(COUNTIF(H8:V8,"<=0")=15,"beyond 15y",COUNTIF(H8:V8,"<=0")+1) | D8: =IF(ISNUMBER(C8),"Migrate by year "&C8,"holds past 15y") | H8: ='Crossover Calculator'!$C$7*((1+B8)^1-1)/B8-('Crossover Calculator'!$C$13+'Crossover Calculator'!$C$11*1) | I8: ='Crossover Calculator'!$C$7*((1+B8)^2-1)/B8-('Crossover Calculator'!$C$13+'Crossover Calculator'!$C$11*2) | J8: ='Crossover Calculator'!$C$7*((1+B8)^3-1)/B8-('Crossover Calculator'!$C$13+'Crossover Calculator'!$C$11*3) | K8: ='Crossover Calculator'!$C$7*((1+B8)^4-1)/B8-('Crossover Calculator'!$C$13+'Crossover Calculator'!$C$11*4) | L8: ='Crossover Calculator'!$C$7*((1+B8)^5-1)/B8-('Crossover Calculator'!$C$13+'Crossover Calculator'!$C$11*5) | M8: ='Crossover Calculator'!$C$7*((1+B8)^6-1)/B8-('Crossover Calculator'!$C$13+'Crossover Calculator'!$C$11*6) | N8: ='Crossover Calculator'!$C$7*((1+B8)^7-1)/B8-('Crossover Calculator'!$C$13+'Crossover Calculator'!$C$11*7) | O8: ='Crossover Calculator'!$C$7*((1+B8)^8-1)/B8-('Crossover Calculator'!$C$13+'Crossover Calculator'!$C$11*8) | P8: ='Crossover Calculator'!$C$7*((1+B8)^9-1)/B8-('Crossover Calculator'!$C$13+'Crossover Calculator'!$C$11*9) | Q8: ='Crossover Calculator'!$C$7*((1+B8)^10-1)/B8-('Crossover Calculator'!$C$13+'Crossover Calculator'!$C$11*10) | R8: ='Crossover Calculator'!$C$7*((1+B8)^11-1)/B8-('Crossover Calculator'!$C$13+'Crossover Calculator'!$C$11*11) | S8: ='Crossover Calculator'!$C$7*((1+B8)^12-1)/B8-('Crossover Calculator'!$C$13+'Crossover Calculator'!$C$11*12) | T8: ='Crossover Calculator'!$C$7*((1+B8)^13-1)/B8-('Crossover Calculator'!$C$13+'Crossover Calculator'!$C$11*13) | U8: ='Crossover Calculator'!$C$7*((1+B8)^14-1)/B8-('Crossover Calculator'!$C$13+'Crossover Calculator'!$C$11*14) | V8: ='Crossover Calculator'!$C$7*((1+B8)^15-1)/B8-('Crossover Calculator'!$C$13+'Crossover Calculator'!$C$11*15)
B9: 0.2 | C9: =IF(COUNTIF(H9:V9,"<=0")=15,"beyond 15y",COUNTIF(H9:V9,"<=0")+1) | D9: =IF(ISNUMBER(C9),"Migrate by year "&C9,"holds past 15y") | H9: ='Crossover Calculator'!$C$7*((1+B9)^1-1)/B9-('Crossover Calculator'!$C$13+'Crossover Calculator'!$C$11*1) | I9: ='Crossover Calculator'!$C$7*((1+B9)^2-1)/B9-('Crossover Calculator'!$C$13+'Crossover Calculator'!$C$11*2) | J9: ='Crossover Calculator'!$C$7*((1+B9)^3-1)/B9-('Crossover Calculator'!$C$13+'Crossover Calculator'!$C$11*3) | K9: ='Crossover Calculator'!$C$7*((1+B9)^4-1)/B9-('Crossover Calculator'!$C$13+'Crossover Calculator'!$C$11*4) | L9: ='Crossover Calculator'!$C$7*((1+B9)^5-1)/B9-('Crossover Calculator'!$C$13+'Crossover Calculator'!$C$11*5) | M9: ='Crossover Calculator'!$C$7*((1+B9)^6-1)/B9-('Crossover Calculator'!$C$13+'Crossover Calculator'!$C$11*6) | N9: ='Crossover Calculator'!$C$7*((1+B9)^7-1)/B9-('Crossover Calculator'!$C$13+'Crossover Calculator'!$C$11*7) | O9: ='Crossover Calculator'!$C$7*((1+B9)^8-1)/B9-('Crossover Calculator'!$C$13+'Crossover Calculator'!$C$11*8) | P9: ='Crossover Calculator'!$C$7*((1+B9)^9-1)/B9-('Crossover Calculator'!$C$13+'Crossover Calculator'!$C$11*9) | Q9: ='Crossover Calculator'!$C$7*((1+B9)^10-1)/B9-('Crossover Calculator'!$C$13+'Crossover Calculator'!$C$11*10) | R9: ='Crossover Calculator'!$C$7*((1+B9)^11-1)/B9-('Crossover Calculator'!$C$13+'Crossover Calculator'!$C$11*11) | S9: ='Crossover Calculator'!$C$7*((1+B9)^12-1)/B9-('Crossover Calculator'!$C$13+'Crossover Calculator'!$C$11*12) | T9: ='Crossover Calculator'!$C$7*((1+B9)^13-1)/B9-('Crossover Calculator'!$C$13+'Crossover Calculator'!$C$11*13) | U9: ='Crossover Calculator'!$C$7*((1+B9)^14-1)/B9-('Crossover Calculator'!$C$13+'Crossover Calculator'!$C$11*14) | V9: ='Crossover Calculator'!$C$7*((1+B9)^15-1)/B9-('Crossover Calculator'!$C$13+'Crossover Calculator'!$C$11*15)
B10: 0.25 | C10: =IF(COUNTIF(H10:V10,"<=0")=15,"beyond 15y",COUNTIF(H10:V10,"<=0")+1) | D10: =IF(ISNUMBER(C10),"Migrate by year "&C10,"holds past 15y") | H10: ='Crossover Calculator'!$C$7*((1+B10)^1-1)/B10-('Crossover Calculator'!$C$13+'Crossover Calculator'!$C$11*1) | I10: ='Crossover Calculator'!$C$7*((1+B10)^2-1)/B10-('Crossover Calculator'!$C$13+'Crossover Calculator'!$C$11*2) | J10: ='Crossover Calculator'!$C$7*((1+B10)^3-1)/B10-('Crossover Calculator'!$C$13+'Crossover Calculator'!$C$11*3) | K10: ='Crossover Calculator'!$C$7*((1+B10)^4-1)/B10-('Crossover Calculator'!$C$13+'Crossover Calculator'!$C$11*4) | L10: ='Crossover Calculator'!$C$7*((1+B10)^5-1)/B10-('Crossover Calculator'!$C$13+'Crossover Calculator'!$C$11*5) | M10: ='Crossover Calculator'!$C$7*((1+B10)^6-1)/B10-('Crossover Calculator'!$C$13+'Crossover Calculator'!$C$11*6) | N10: ='Crossover Calculator'!$C$7*((1+B10)^7-1)/B10-('Crossover Calculator'!$C$13+'Crossover Calculator'!$C$11*7) | O10: ='Crossover Calculator'!$C$7*((1+B10)^8-1)/B10-('Crossover Calculator'!$C$13+'Crossover Calculator'!$C$11*8) | P10: ='Crossover Calculator'!$C$7*((1+B10)^9-1)/B10-('Crossover Calculator'!$C$13+'Crossover Calculator'!$C$11*9) | Q10: ='Crossover Calculator'!$C$7*((1+B10)^10-1)/B10-('Crossover Calculator'!$C$13+'Crossover Calculator'!$C$11*10) | R10: ='Crossover Calculator'!$C$7*((1+B10)^11-1)/B10-('Crossover Calculator'!$C$13+'Crossover Calculator'!$C$11*11) | S10: ='Crossover Calculator'!$C$7*((1+B10)^12-1)/B10-('Crossover Calculator'!$C$13+'Crossover Calculator'!$C$11*12) | T10: ='Crossover Calculator'!$C$7*((1+B10)^13-1)/B10-('Crossover Calculator'!$C$13+'Crossover Calculator'!$C$11*13) | U10: ='Crossover Calculator'!$C$7*((1+B10)^14-1)/B10-('Crossover Calculator'!$C$13+'Crossover Calculator'!$C$11*14) | V10: ='Crossover Calculator'!$C$7*((1+B10)^15-1)/B10-('Crossover Calculator'!$C$13+'Crossover Calculator'!$C$11*15)
B11: 0.3 | C11: =IF(COUNTIF(H11:V11,"<=0")=15,"beyond 15y",COUNTIF(H11:V11,"<=0")+1) | D11: =IF(ISNUMBER(C11),"Migrate by year "&C11,"holds past 15y") | H11: ='Crossover Calculator'!$C$7*((1+B11)^1-1)/B11-('Crossover Calculator'!$C$13+'Crossover Calculator'!$C$11*1) | I11: ='Crossover Calculator'!$C$7*((1+B11)^2-1)/B11-('Crossover Calculator'!$C$13+'Crossover Calculator'!$C$11*2) | J11: ='Crossover Calculator'!$C$7*((1+B11)^3-1)/B11-('Crossover Calculator'!$C$13+'Crossover Calculator'!$C$11*3) | K11: ='Crossover Calculator'!$C$7*((1+B11)^4-1)/B11-('Crossover Calculator'!$C$13+'Crossover Calculator'!$C$11*4) | L11: ='Crossover Calculator'!$C$7*((1+B11)^5-1)/B11-('Crossover Calculator'!$C$13+'Crossover Calculator'!$C$11*5) | M11: ='Crossover Calculator'!$C$7*((1+B11)^6-1)/B11-('Crossover Calculator'!$C$13+'Crossover Calculator'!$C$11*6) | N11: ='Crossover Calculator'!$C$7*((1+B11)^7-1)/B11-('Crossover Calculator'!$C$13+'Crossover Calculator'!$C$11*7) | O11: ='Crossover Calculator'!$C$7*((1+B11)^8-1)/B11-('Crossover Calculator'!$C$13+'Crossover Calculator'!$C$11*8) | P11: ='Crossover Calculator'!$C$7*((1+B11)^9-1)/B11-('Crossover Calculator'!$C$13+'Crossover Calculator'!$C$11*9) | Q11: ='Crossover Calculator'!$C$7*((1+B11)^10-1)/B11-('Crossover Calculator'!$C$13+'Crossover Calculator'!$C$11*10) | R11: ='Crossover Calculator'!$C$7*((1+B11)^11-1)/B11-('Crossover Calculator'!$C$13+'Crossover Calculator'!$C$11*11) | S11: ='Crossover Calculator'!$C$7*((1+B11)^12-1)/B11-('Crossover Calculator'!$C$13+'Crossover Calculator'!$C$11*12) | T11: ='Crossover Calculator'!$C$7*((1+B11)^13-1)/B11-('Crossover Calculator'!$C$13+'Crossover Calculator'!$C$11*13) | U11: ='Crossover Calculator'!$C$7*((1+B11)^14-1)/B11-('Crossover Calculator'!$C$13+'Crossover Calculator'!$C$11*14) | V11: ='Crossover Calculator'!$C$7*((1+B11)^15-1)/B11-('Crossover Calculator'!$C$13+'Crossover Calculator'!$C$11*15)
B12: 0.4 | C12: =IF(COUNTIF(H12:V12,"<=0")=15,"beyond 15y",COUNTIF(H12:V12,"<=0")+1) | D12: =IF(ISNUMBER(C12),"Migrate by year "&C12,"holds past 15y") | H12: ='Crossover Calculator'!$C$7*((1+B12)^1-1)/B12-('Crossover Calculator'!$C$13+'Crossover Calculator'!$C$11*1) | I12: ='Crossover Calculator'!$C$7*((1+B12)^2-1)/B12-('Crossover Calculator'!$C$13+'Crossover Calculator'!$C$11*2) | J12: ='Crossover Calculator'!$C$7*((1+B12)^3-1)/B12-('Crossover Calculator'!$C$13+'Crossover Calculator'!$C$11*3) | K12: ='Crossover Calculator'!$C$7*((1+B12)^4-1)/B12-('Crossover Calculator'!$C$13+'Crossover Calculator'!$C$11*4) | L12: ='Crossover Calculator'!$C$7*((1+B12)^5-1)/B12-('Crossover Calculator'!$C$13+'Crossover Calculator'!$C$11*5) | M12: ='Crossover Calculator'!$C$7*((1+B12)^6-1)/B12-('Crossover Calculator'!$C$13+'Crossover Calculator'!$C$11*6) | N12: ='Crossover Calculator'!$C$7*((1+B12)^7-1)/B12-('Crossover Calculator'!$C$13+'Crossover Calculator'!$C$11*7) | O12: ='Crossover Calculator'!$C$7*((1+B12)^8-1)/B12-('Crossover Calculator'!$C$13+'Crossover Calculator'!$C$11*8) | P12: ='Crossover Calculator'!$C$7*((1+B12)^9-1)/B12-('Crossover Calculator'!$C$13+'Crossover Calculator'!$C$11*9) | Q12: ='Crossover Calculator'!$C$7*((1+B12)^10-1)/B12-('Crossover Calculator'!$C$13+'Crossover Calculator'!$C$11*10) | R12: ='Crossover Calculator'!$C$7*((1+B12)^11-1)/B12-('Crossover Calculator'!$C$13+'Crossover Calculator'!$C$11*11) | S12: ='Crossover Calculator'!$C$7*((1+B12)^12-1)/B12-('Crossover Calculator'!$C$13+'Crossover Calculator'!$C$11*12) | T12: ='Crossover Calculator'!$C$7*((1+B12)^13-1)/B12-('Crossover Calculator'!$C$13+'Crossover Calculator'!$C$11*13) | U12: ='Crossover Calculator'!$C$7*((1+B12)^14-1)/B12-('Crossover Calculator'!$C$13+'Crossover Calculator'!$C$11*14) | V12: ='Crossover Calculator'!$C$7*((1+B12)^15-1)/B12-('Crossover Calculator'!$C$13+'Crossover Calculator'!$C$11*15)
B14: Columns H-V are a helper grid (keep cumulative minus replace cumulative, years 1-15). Leave them alone.
