Workbook

Sheet Start Here
B2: Unit Economics & Cost-Curve Simulator
B3: Companion to "Cost as a Non-Functional Requirement: The Frugal Architect" (Engineering Economics, Part 3)
B5: What this answers
B6: As your product scales, does cost per unit fall, hold, or rise against revenue per unit? That one
B7: question decides whether growth makes you healthier or quietly kills you. This tool plots your cost
B8: and revenue curves from today's volume out to 1000x and flags the volume where margin goes negative.
B10: The three curves (Vogels' Law II: align cost to the business)
B11: - Sublinear (exponent < 1): cost per unit FALLS as you scale. Caching, batching, amortized fixed cost.
B12: Growth helps you. This is the curve you want.
B13: - Linear (exponent = 1): cost per unit HOLDS. No scale economy. Big just means unprofitable bigger.
B14: - Superlinear (exponent > 1): cost per unit RISES. Coordination overhead, chatty services, data that
B15: gets pricier to query. Growth actively hurts; there's a wall ahead.
... B33: - Defaults reproduce the article's document-processing example ($0.002 cost, $0.005 price, 60% margin).

Sheet Unit Economics
B2: Unit Economics (today's snapshot)
B3: Edit the blue cells. Confirm gross margin is positive before you worry about scale.
B5: INPUTS
B6: Monthly infrastructure spend ($) | C6: 80000 | E6: Total relevant infra cost for this workload.
B7: Units of value per month | C7: 40000000 | E7: Your chosen unit: documents, requests, transactions, inferences.
B8: Price charged per unit ($) | C8: 0.005 | E8: Average revenue per unit.
B10: RESULTS
B11: Cost per unit ($) | C11: =$C$6/$C$7 | E11: Infra spend divided by units.
B12: Revenue per unit ($) | C12: =$C$8 | E12: What you charge.
B13: Gross margin per unit ($) | C13: =$C$8-$C$6/$C$7 | E13: Price minus cost per unit.
B14: Gross margin (%) | C14: =($C$8-$C$6/$C$7)/$C$8 | E14: The headline number.
B15: Monthly revenue ($) | C15: =$C$8*$C$7 | E15: Price times volume.
B16: Monthly gross profit ($) | C16: =$C$8*$C$7-$C$6 | E16: Revenue minus infra spend.
B18: Health check | C18: =IF($C$8>$C$6/$C$7,"Positive margin. Now go check the Scale Projection tab.","NEGATIVE margin: you lose money on every unit today. Fix price or cost before scaling.")

Sheet Scale Projection
B2: Scale Projection: the 10x question
B3: Pick a cost-scaling exponent and watch cost per unit and margin across 1x to 1000x.
B5: INPUT
B6: Cost-scaling exponent (0.7=sublinear, 1.0=linear, 1.2=superlinear) | C6: 0.85 | E6: How cost scales with volume. <1 cheaper per unit as you grow; >1 pricier.
B10: 1x | C10: ='Unit Economics'!$C$7*1 | D10: ='Unit Economics'!$C$6*1^$C$6 | E10: =D10/C10 | F10: =('Unit Economics'!$C$8-E10)/'Unit Economics'!$C$8 | G10: ='Unit Economics'!$C$8*C10-D10
B11: 2x | C11: ='Unit Economics'!$C$7*2 | D11: ='Unit Economics'!$C$6*2^$C$6 | E11: =D11/C11 | F11: =('Unit Economics'!$C$8-E11)/'Unit Economics'!$C$8 | G11: ='Unit Economics'!$C$8*C11-D11
B12: 5x | C12: ='Unit Economics'!$C$7*5 | D12: ='Unit Economics'!$C$6*5^$C$6 | E12: =D12/C12 | F12: =('Unit Economics'!$C$8-E12)/'Unit Economics'!$C$8 | G12: ='Unit Economics'!$C$8*C12-D12
B13: 10x | C13: ='Unit Economics'!$C$7*10 | D13: ='Unit Economics'!$C$6*10^$C$6 | E13: =D13/C13 | F13: =('Unit Economics'!$C$8-E13)/'Unit Economics'!$C$8 | G13: ='Unit Economics'!$C$8*C13-D13
B14: 25x | C14: ='Unit Economics'!$C$7*25 | D14: ='Unit Economics'!$C$6*25^$C$6 | E14: =D14/C14 | F14: =('Unit Economics'!$C$8-E14)/'Unit Economics'!$C$8 | G14: ='Unit Economics'!$C$8*C14-D14
B15: 50x | C15: ='Unit Economics'!$C$7*50 | D15: ='Unit Economics'!$C$6*50^$C$6 | E15: =D15/C15 | F15: =('Unit Economics'!$C$8-E15)/'Unit Economics'!$C$8 | G15: ='Unit Economics'!$C$8*C15-D15
B16: 100x | C16: ='Unit Economics'!$C$7*100 | D16: ='Unit Economics'!$C$6*100^$C$6 | E16: =D16/C16 | F16: =('Unit Economics'!$C$8-E16)/'Unit Economics'!$C$8 | G16: ='Unit Economics'!$C$8*C16-D16
B17: 250x | C17: ='Unit Economics'!$C$7*250 | D17: ='Unit Economics'!$C$6*250^$C$6 | E17: =D17/C17 | F17: =('Unit Economics'!$C$8-E17)/'Unit Economics'!$C$8 | G17: ='Unit Economics'!$C$8*C17-D17
B18: 500x | C18: ='Unit Economics'!$C$7*500 | D18: ='Unit Economics'!$C$6*500^$C$6 | E18: =D18/C18 | F18: =('Unit Economics'!$C$8-E18)/'Unit Economics'!$C$8 | G18: ='Unit Economics'!$C$8*C18-D18
B19: 1000x | C19: ='Unit Economics'!$C$7*1000 | D19: ='Unit Economics'!$C$6*1000^$C$6 | E19: =D19/C19 | F19: =('Unit Economics'!$C$8-E19)/'Unit Economics'!$C$8 | G19: ='Unit Economics'!$C$8*C19-D19
B21: Curve type | C21: =IF($C$6<0.99,"Sublinear - growth helps you",IF($C$6>1.01,"Superlinear - growth hurts you","Linear - no scale economy"))
B22: Margin at 1000x | C22: =F19
B23: Verdict | C23: =IF(F19<0,"Margin goes NEGATIVE before 1000x. Redesign the cost curve now, while it is cheap.","Margin stays positive through 1000x at this exponent.")

Sheet Sensitivity
B2: Sensitivity: cost-scaling exponent
B3: The exponent is the assumption you are least sure of. Here is the margin at each scale for a range of exponents.
B5: Exponent \ Scale | C5: 1x margin | D5: 10x margin | E5: 100x margin | F5: 1000x margin
B6: 0.7 | C6: =('Unit Economics'!$C$8-('Unit Economics'!$C$6*1^B6)/('Unit Economics'!$C$7*1))/'Unit Economics'!$C$8 | D6: =('Unit Economics'!$C$8-('Unit Economics'!$C$6*10^B6)/('Unit Economics'!$C$7*10))/'Unit Economics'!$C$8 | E6: =('Unit Economics'!$C$8-('Unit Economics'!$C$6*100^B6)/('Unit Economics'!$C$7*100))/'Unit Economics'!$C$8 | F6: =('Unit Economics'!$C$8-('Unit Economics'!$C$6*1000^B6)/('Unit Economics'!$C$7*1000))/'Unit Economics'!$C$8
B7: 0.8 | C7: =('Unit Economics'!$C$8-('Unit Economics'!$C$6*1^B7)/('Unit Economics'!$C$7*1))/'Unit Economics'!$C$8 | D7: =('Unit Economics'!$C$8-('Unit Economics'!$C$6*10^B7)/('Unit Economics'!$C$7*10))/'Unit Economics'!$C$8 | E7: =('Unit Economics'!$C$8-('Unit Economics'!$C$6*100^B7)/('Unit Economics'!$C$7*100))/'Unit Economics'!$C$8 | F7: =('Unit Economics'!$C$8-('Unit Economics'!$C$6*1000^B7)/('Unit Economics'!$C$7*1000))/'Unit Economics'!$C$8
B8: 0.9 | C8: =('Unit Economics'!$C$8-('Unit Economics'!$C$6*1^B8)/('Unit Economics'!$C$7*1))/'Unit Economics'!$C$8 | D8: =('Unit Economics'!$C$8-('Unit Economics'!$C$6*10^B8)/('Unit Economics'!$C$7*10))/'Unit Economics'!$C$8 | E8: =('Unit Economics'!$C$8-('Unit Economics'!$C$6*100^B8)/('Unit Economics'!$C$7*100))/'Unit Economics'!$C$8 | F8: =('Unit Economics'!$C$8-('Unit Economics'!$C$6*1000^B8)/('Unit Economics'!$C$7*1000))/'Unit Economics'!$C$8
B9: 1 | C9: =('Unit Economics'!$C$8-('Unit Economics'!$C$6*1^B9)/('Unit Economics'!$C$7*1))/'Unit Economics'!$C$8 | D9: =('Unit Economics'!$C$8-('Unit Economics'!$C$6*10^B9)/('Unit Economics'!$C$7*10))/'Unit Economics'!$C$8 | E9: =('Unit Economics'!$C$8-('Unit Economics'!$C$6*100^B9)/('Unit Economics'!$C$7*100))/'Unit Economics'!$C$8 | F9: =('Unit Economics'!$C$8-('Unit Economics'!$C$6*1000^B9)/('Unit Economics'!$C$7*1000))/'Unit Economics'!$C$8
B10: 1.1 | C10: =('Unit Economics'!$C$8-('Unit Economics'!$C$6*1^B10)/('Unit Economics'!$C$7*1))/'Unit Economics'!$C$8 | D10: =('Unit Economics'!$C$8-('Unit Economics'!$C$6*10^B10)/('Unit Economics'!$C$7*10))/'Unit Economics'!$C$8 | E10: =('Unit Economics'!$C$8-('Unit Economics'!$C$6*100^B10)/('Unit Economics'!$C$7*100))/'Unit Economics'!$C$8 | F10: =('Unit Economics'!$C$8-('Unit Economics'!$C$6*1000^B10)/('Unit Economics'!$C$7*1000))/'Unit Economics'!$C$8
B11: 1.2 | C11: =('Unit Economics'!$C$8-('Unit Economics'!$C$6*1^B11)/('Unit Economics'!$C$7*1))/'Unit Economics'!$C$8 | D11: =('Unit Economics'!$C$8-('Unit Economics'!$C$6*10^B11)/('Unit Economics'!$C$7*10))/'Unit Economics'!$C$8 | E11: =('Unit Economics'!$C$8-('Unit Economics'!$C$6*100^B11)/('Unit Economics'!$C$7*100))/'Unit Economics'!$C$8 | F11: =('Unit Economics'!$C$8-('Unit Economics'!$C$6*1000^B11)/('Unit Economics'!$C$7*1000))/'Unit Economics'!$C$8
B13: Read down a column: as the exponent rises past 1.0, scale turns from reward into margin collapse.
